MANIFEST.in
README.rst
requirements.txt
setup.cfg
setup.py
djmicrosip_actualizarcosto/__init__.py
djmicrosip_actualizarcosto/__init__.pyc
djmicrosip_actualizarcosto/config.pyc
djmicrosip_actualizarcosto/forms.pyc
djmicrosip_actualizarcosto/models.pyc
djmicrosip_actualizarcosto/urls.pyc
djmicrosip_actualizarcosto/views.pyc
djmicrosip_actualizarcosto.egg-info/PKG-INFO
djmicrosip_actualizarcosto.egg-info/SOURCES.txt
djmicrosip_actualizarcosto.egg-info/dependency_links.txt
djmicrosip_actualizarcosto.egg-info/requires.txt
djmicrosip_actualizarcosto.egg-info/top_level.txt
djmicrosip_actualizarcosto/static/djmicrosip_actualizarcosto/js/actualizar.js
djmicrosip_actualizarcosto/templates/djmicrosip_actualizarcosto/actualizar.html
djmicrosip_actualizarcosto/templates/djmicrosip_actualizarcosto/articulo.html
djmicrosip_actualizarcosto/templates/djmicrosip_actualizarcosto/base.html
djmicrosip_actualizarcosto/templates/djmicrosip_actualizarcosto/index.html